{"AdditionalFields":[{"Key":"AACROrganSiteAll","Value":""},{"Key":"AACRTrackAll","Value":"Clinical Research"},{"Key":"CEHoursPP8","Value":"1.5"},{"Key":"LivecastUrl","Value":""},{"Key":"RelatedArticlesProgPlan","Value":""},{"Key":"SessionCategoryBasic","Value":""},{"Key":"SessionName","Value":"Major Symposium"},{"Key":"VideoType","Value":""},{"Key":"WebcastIPSessionLink","Value":""},{"Key":"Presentation Count","Value":"9"}],"BoothSponsorshipIdForCalendar":null,"BoothSponsorshipIdForDetail":null,"BoothSponsorshipIdForResult":null,"CSlideId":null,"Color":"","ContentCaptureVendorSpecification":null,"Created":null,"Date":"2024-04-08","Description":"This session will focus on neoadjuvant therapy for three major types of cancer: breast cancer, melanoma, and sarcoma. The panel consists of medical and surgical oncologists who will delve into the critical issues surrounding the assessment of effectiveness of neoadjuvant therapy, specifically focusing on endpoints for evaluation. We will explore the latest advancements in this field and discuss the newest targets and pathways and opportunities for de-escalation of local-regional therapies in cases of exceptional response. This session promises to be enlightening and thought-provoking, shedding light on the evolving landscape of neoadjuvant therapy. Attendees can expect to gain valuable insights from the collective wisdom of the speakers, paving the way for improved treatment strategies and outcomes for patients battling these challenging cancers.","Duration":90,"EmbargoSessionContentRule":null,"EmbargoSessionContentUntil":null,"End":"4\/8\/2024 2:00:00 PM","EndTime":"14:00","HidePresentationRating":"False","HidePresentations":"False","Id":"138","Key":"dd785fb4-e23f-4336-9679-3183e3d7b760","LastUpdated":"2024-03-07 22:18","LimitCMEToRegistrationCodes":null,"LimitMediaToRegistrationCodes":null,"Location":"Ballroom 6 B - Upper Level - Convention Center","MediaSource":"None","MediaSourceDetails":null,"MediaSourceDuration":null,"MediaSourceDurationHMS":null,"Notes":null,"Number":"SY24","OnDemand":"False","OwnerKey":null,"PlayerUrl":null,"PlayerUrlReason":null,"PrimaryCategory":"","PrimaryCategory_keys":"","PrimaryMediaItemId":null,"PrimaryMediaItemKey":null,"RuleStatus":"Incomplete","SearchResultBody":"SY24. Neoadjuvant Therapies","SearchResultCalendarDisplayBlock":null,"SearchResultFooter":"Ballroom 6 B - Upper Level - Convention Center","SearchResultHeader":"Apr  8 2024 12:30PM","SecondaryCategory":"","SecondaryCategory_keys":"","ShowChatLink":null,"Start":"4\/8\/2024 12:30:00 PM","StartTime":"12:30","Status":"Active","StreamingConfiguration":null,"StreamingKey":null,"ThumbnailUrl":null,"Title":"Neoadjuvant Therapies","Type":null,"TypeKey":null}