{"AdditionalFields":[{"Key":"AACROrganSiteAll","Value":""},{"Key":"AACRTrackAll","Value":"Prevention \/ Early Detection \/ Interception"},{"Key":"CEHoursPP8","Value":""},{"Key":"LivecastUrl","Value":""},{"Key":"RelatedArticlesProgPlan","Value":""},{"Key":"SessionCategoryBasic","Value":"Prevention \/ Early Detection \/ Interception"},{"Key":"SessionName","Value":"Poster Session"},{"Key":"VideoType","Value":""},{"Key":"WebcastIPSessionLink","Value":""},{"Key":"Presentation Count","Value":"19"}],"BoothSponsorshipIdForCalendar":null,"BoothSponsorshipIdForDetail":null,"BoothSponsorshipIdForResult":null,"CSlideId":null,"Color":"","ContentCaptureVendorSpecification":null,"Created":null,"Date":"2024-04-08","Description":null,"Duration":210,"EmbargoSessionContentRule":null,"EmbargoSessionContentUntil":null,"End":"4\/8\/2024 5:00:00 PM","EndTime":"17:00","HidePresentationRating":"False","HidePresentations":"False","Id":"411","Key":"aabee9df-25c2-4fc8-9805-05a03a80a03e","LastUpdated":"2024-03-07 22:18","LimitCMEToRegistrationCodes":null,"LimitMediaToRegistrationCodes":null,"Location":"Section 30","MediaSource":"None","MediaSourceDetails":null,"MediaSourceDuration":null,"MediaSourceDurationHMS":null,"Notes":null,"Number":"PO.PR02.03","OnDemand":"False","OwnerKey":null,"PlayerUrl":null,"PlayerUrlReason":null,"PrimaryCategory":"","PrimaryCategory_keys":"","PrimaryMediaItemId":null,"PrimaryMediaItemKey":null,"RuleStatus":"Complete","SearchResultBody":"PO.PR02.03. Animal and Cellular Models of Cancer Prevention and the Study of Biological\/Biochemical Mechanisms","SearchResultCalendarDisplayBlock":null,"SearchResultFooter":"Section 30","SearchResultHeader":"Apr  8 2024  1:30PM","SecondaryCategory":"","SecondaryCategory_keys":"","ShowChatLink":null,"Start":"4\/8\/2024 1:30:00 PM","StartTime":"13:30","Status":"Active","StreamingConfiguration":null,"StreamingKey":null,"ThumbnailUrl":null,"Title":"Animal and Cellular Models of Cancer Prevention and the Study of Biological\/Biochemical Mechanisms","Type":null,"TypeKey":null}